{
  "feature": "figma_web",
  "vhash": "ca2c71fd",
  "commit": "61d68a32f3a7dd53d3f138d713b74b061862898f",
  "timestamp": "2026-04-07T13:45:06.336808+00:00",
  "rules": [
    "RULE-1",
    "RULE-10",
    "RULE-11",
    "RULE-12",
    "RULE-13",
    "RULE-14",
    "RULE-15",
    "RULE-2",
    "RULE-3",
    "RULE-4",
    "RULE-5",
    "RULE-6",
    "RULE-7",
    "RULE-8",
    "RULE-9"
  ],
  "proofs": [
    {
      "id": "PROOF-1",
      "rule": "RULE-1",
      "status": "pass"
    },
    {
      "id": "PROOF-10",
      "rule": "RULE-10",
      "status": "pass"
    },
    {
      "id": "PROOF-11",
      "rule": "RULE-11",
      "status": "pass"
    },
    {
      "id": "PROOF-12",
      "rule": "RULE-12",
      "status": "pass"
    },
    {
      "id": "PROOF-13",
      "rule": "RULE-13",
      "status": "pass"
    },
    {
      "id": "PROOF-14",
      "rule": "RULE-14",
      "status": "pass"
    },
    {
      "id": "PROOF-15",
      "rule": "RULE-15",
      "status": "pass"
    },
    {
      "id": "PROOF-2",
      "rule": "RULE-2",
      "status": "pass"
    },
    {
      "id": "PROOF-3",
      "rule": "RULE-3",
      "status": "pass"
    },
    {
      "id": "PROOF-4",
      "rule": "RULE-4",
      "status": "pass"
    },
    {
      "id": "PROOF-5",
      "rule": "RULE-5",
      "status": "pass"
    },
    {
      "id": "PROOF-6",
      "rule": "RULE-6",
      "status": "pass"
    },
    {
      "id": "PROOF-7",
      "rule": "RULE-7",
      "status": "pass"
    },
    {
      "id": "PROOF-8",
      "rule": "RULE-8",
      "status": "pass"
    },
    {
      "id": "PROOF-9",
      "rule": "RULE-9",
      "status": "pass"
    }
  ]
}