{
  "tier": "unit",
  "proofs": [
    {
      "feature": "sync_status",
      "id": "PROOF-1",
      "rule": "RULE-1",
      "test_file": "dev/test_mcp_server.py",
      "test_name": "test_rules_with_required_no_proofs",
      "status": "pass",
      "tier": "unit"
    },
    {
      "feature": "sync_status",
      "id": "PROOF-2",
      "rule": "RULE-2",
      "test_file": "dev/test_mcp_server.py",
      "test_name": "test_ready_with_vhash",
      "status": "pass",
      "tier": "unit"
    },
    {
      "feature": "sync_status",
      "id": "PROOF-3",
      "rule": "RULE-3",
      "test_file": "dev/test_mcp_server.py",
      "test_name": "test_warns_unnumbered_rules",
      "status": "pass",
      "tier": "unit"
    },
    {
      "feature": "sync_status",
      "id": "PROOF-4",
      "rule": "RULE-4",
      "test_file": "dev/test_mcp_server.py",
      "test_name": "test_requires_counts_for_coverage",
      "status": "pass",
      "tier": "unit"
    },
    {
      "feature": "sync_status",
      "id": "PROOF-5",
      "rule": "RULE-5",
      "test_file": "dev/test_mcp_server.py",
      "test_name": "test_manual_proof_staleness",
      "status": "pass",
      "tier": "unit"
    },
    {
      "feature": "sync_status",
      "id": "PROOF-8",
      "rule": "RULE-8",
      "test_file": "dev/test_mcp_server.py",
      "test_name": "test_scan_specs_detects_global",
      "status": "pass",
      "tier": "unit"
    },
    {
      "feature": "sync_status",
      "id": "PROOF-9",
      "rule": "RULE-9",
      "test_file": "dev/test_mcp_server.py",
      "test_name": "test_global_anchor_auto_applies",
      "status": "pass",
      "tier": "unit"
    },
    {
      "feature": "sync_status",
      "id": "PROOF-10",
      "rule": "RULE-10",
      "test_file": "dev/test_mcp_server.py",
      "test_name": "test_rule_labels",
      "status": "pass",
      "tier": "unit"
    },
    {
      "feature": "sync_status",
      "id": "PROOF-11",
      "rule": "RULE-11",
      "test_file": "dev/test_mcp_server.py",
      "test_name": "test_scope_overlap_suggestion",
      "status": "pass",
      "tier": "unit"
    },
    {
      "feature": "sync_status",
      "id": "PROOF-7",
      "rule": "RULE-7",
      "test_file": "dev/test_mcp_server.py",
      "test_name": "test_structural_only_detection",
      "status": "pass",
      "tier": "unit"
    },
    {
      "feature": "sync_status",
      "id": "PROOF-12",
      "rule": "RULE-12",
      "test_file": "dev/test_mcp_server.py",
      "test_name": "test_unresolved_requires_warning",
      "status": "pass",
      "tier": "unit"
    },
    {
      "feature": "sync_status",
      "id": "PROOF-15",
      "rule": "RULE-15",
      "test_file": "dev/test_mcp_server.py",
      "test_name": "test_receipt_staleness_from_anchor_change",
      "status": "pass",
      "tier": "unit"
    },
    {
      "feature": "sync_status",
      "id": "PROOF-13",
      "rule": "RULE-13",
      "test_file": "dev/test_mcp_server.py",
      "test_name": "test_manual_proof_without_scope_warning",
      "status": "pass",
      "tier": "unit"
    },
    {
      "feature": "sync_status",
      "id": "PROOF-14",
      "rule": "RULE-14",
      "test_file": "dev/test_mcp_server.py",
      "test_name": "test_prefers_subdirectory_proofs",
      "status": "pass",
      "tier": "unit"
    },
    {
      "feature": "sync_status",
      "id": "PROOF-13",
      "rule": "RULE-13",
      "test_file": "dev/test_mcp_server.py",
      "test_name": "test_manual_proof_with_scope_no_warning",
      "status": "pass",
      "tier": "unit"
    },
    {
      "feature": "sync_status",
      "id": "PROOF-7",
      "rule": "RULE-7",
      "test_file": "dev/test_mcp_server.py",
      "test_name": "test_structural_regex_rejects_behavioral_descriptions",
      "status": "pass",
      "tier": "unit"
    },
    {
      "feature": "sync_status",
      "id": "PROOF-7",
      "rule": "RULE-7",
      "test_file": "dev/test_mcp_server.py",
      "test_name": "test_structural_regex_accepts_grep_descriptions",
      "status": "pass",
      "tier": "unit"
    },
    {
      "feature": "sync_status",
      "id": "PROOF-16",
      "rule": "RULE-16",
      "test_file": "dev/test_mcp_server.py",
      "test_name": "test_warns_uncommitted_spec_changes",
      "status": "pass",
      "tier": "unit"
    },
    {
      "feature": "sync_status",
      "id": "PROOF-18",
      "rule": "RULE-18",
      "test_file": "dev/test_mcp_server.py",
      "test_name": "test_summary_table",
      "status": "pass",
      "tier": "unit"
    },
    {
      "feature": "sync_status",
      "id": "PROOF-6",
      "rule": "RULE-6",
      "test_file": "dev/test_mcp_server.py",
      "test_name": "test_vhash_with_prefixed_keys",
      "status": "pass",
      "tier": "unit"
    }
  ]
}
